pys3thon/__init__.py
pys3thon/opendal/__init__.py
pys3thon/opendal/service.py
pys3thon/opendal/shared.py
pys3thon/opendal/s3/__init__.py
pys3thon/opendal/s3/client.py
pys3thon/opendal/s3/descriptor.py
pys3thon/s3/__init__.py
pys3thon/s3/client.py
pys3thon/utils/__init__.py
pys3thon/utils/cryptography.py
pys3thon/utils/run_shell_command.py
pys3thon-0.7.3.dist-info/LICENSE
pys3thon-0.7.3.dist-info/METADATA
pys3thon-0.7.3.dist-info/WHEEL
pys3thon-0.7.3.dist-info/top_level.txt
pys3thon-0.7.3.dist-info/RECORD
