Metadata-Version: 2.1
Name: pys3thon
Version: 0.7.3
Author: Kevin Lu
Author-email: kevinyihchyunlu@gmail.com
License: MIT
License-File: LICENSE
Requires-Dist: boto3>=1.24.89
Requires-Dist: tqdm>=4.64.0
Requires-Dist: pyOpenSSL==22.1.0
Requires-Dist: opendal>=0.45.2
Requires-Dist: smart-open==7.1.0
Requires-Dist: asgiref==3.8.1
Provides-Extra: dev
Requires-Dist: pytest==7.1.3; extra == "dev"
Requires-Dist: pytest-mock==3.10.0; extra == "dev"
Requires-Dist: pytest-only; extra == "dev"
Requires-Dist: python-semantic-release==7.32.1; extra == "dev"
Requires-Dist: moto>=5.0; extra == "dev"
Requires-Dist: flake8==5.0.4; extra == "dev"
Requires-Dist: black==22.10.0; extra == "dev"
Requires-Dist: isort==5.10.1; extra == "dev"
Requires-Dist: pytest-watcher==0.4.3; extra == "dev"
Requires-Dist: pre-commit==2.20.0; extra == "dev"
Requires-Dist: click==8.1.3; extra == "dev"
Requires-Dist: python-dotenv==1.0.1; extra == "dev"
